[
    {
        "component_name": "",
        "root_vs": "",
        "draw_vb": "0b5bd46e",
        "position_vb": "0b5bd46e",
        "blend_vb": "",
        "texcoord_vb": "c2a2293a",
        "ib": "e2f8011c",
        "object_indexes": [
            0
        ],
        "object_classifications": [
            "Head"
        ],
        "texture_hashes": [
            [
                [
                    "Diffuse",
                    ".dds",
                    "0cd456af"
                ],
                [
                    "LightMap",
                    ".dds",
                    "d4841e1a"
                ]
            ]
        ]
    }
]